Metadata-Version: 1.1
Name: Flask-Registry
Version: 0.2.0
Summary: Flask-Registry is an extension for Flask that allow frameworks to dynamically assemble your Flask application from reusable packages consisting of blueprints, extensions, and configurations.
Home-page: http://github.com/inveniosoftware/flask-registry/
Author: Invenio collaboration
Author-email: info@invenio-software.org
License: GPLv2
Platform: any
Classifier: Environment :: Web Environment
Classifier: Intended Audience :: Developers
Classifier: License :: OSI Approved :: GNU General Public License v2 (GPLv2)
Classifier: Operating System :: OS Independent
Classifier: Programming Language :: Python
Classifier: Topic :: Internet :: WWW/HTTP :: Dynamic Content
Classifier: Topic :: Software Development :: Libraries :: Python Modules
Classifier: Programming Language :: Python :: 2
Classifier: Programming Language :: Python :: 2.6
Classifier: Programming Language :: Python :: 2.7
Classifier: Programming Language :: Python :: 3
Classifier: Programming Language :: Python :: 3.3
Classifier: Development Status :: 5 - Production/Stable
